bookstack/__init__.py
bookstack/__version__.py
bookstack/models.py
bookstack/utils.py
bookstack-0.1.0b0.dist-info/LICENSE
bookstack-0.1.0b0.dist-info/METADATA
bookstack-0.1.0b0.dist-info/WHEEL
bookstack-0.1.0b0.dist-info/top_level.txt
bookstack-0.1.0b0.dist-info/RECORD
