Metadata-Version: 2.1
Name: bookstack
Version: 0.1.0b0
Summary: A Python wrapper for BookStack's API
Home-page: https://github.com/coffeepenbit/bookstack
Author: coffeepenbit
Author-email: coffeepenbit@gmail.com
License: UNKNOWN
Platform: UNKNOWN
Classifier: Programming Language :: Python :: 3
Classifier: License :: OSI Approved :: MIT License
Classifier: Operating System :: OS Independent
Requires-Python: >=3.6
Requires-Dist: requests (<3,>=2.18)
Requires-Dist: cached-property (<2,>=1.5)
Requires-Dist: inflection (==0.4)
Provides-Extra: dev
Requires-Dist: bump2version ; extra == 'dev'
Requires-Dist: pylint ; extra == 'dev'
Requires-Dist: pytest ; extra == 'dev'
Requires-Dist: pytest-cov ; extra == 'dev'
Requires-Dist: pytest-vcr ; extra == 'dev'
Requires-Dist: tox ; extra == 'dev'
